ALU.v
module ALU(
    input wire signed [31: 0] A, B,
    input wire [2:0] ALUControl,
    output reg signed [31:0] Result,
    output reg Zero, Negative, Overflow, Carry
);

reg signed [32:0] temp;
localparam ADD = 3'b000, SUB = 3'b001, AND = 3'b010, OR = 3'b011, SLT = 3'b101;

always @(*) begin
    Zero = 0;
    Negative = 0;
    Overflow = 0;
    Carry = 0;

    case (ALUControl)
        ADD:begin
            temp = {1'b0, A} + {1'b0, B};
            Result = temp[31:0];
        end
        SUB: Result = A - B;
        AND: Result = A & B;
        OR: Result = A ^ B;
        SLT: Result = A < B;
        default: Result = 0;
    endcase

    if(Result == 0)
        Zero = 1;
    else if(Result < 0) begin
        case (ALUControl)
            ADD: begin
                if(A > 0 && B > 0)
                    Overflow = 1;
            end
            SUB: begin
                if(A > 0 && B < 0)
                    Overflow = 1;
            end
        endcase
        Negative = 1;
    end
    else begin
        case (ALUControl)
            ADD: begin
                if(A < 0 && B < 0)
                    Overflow = 1;
            end
            SUB: begin
                if(A < 0 && B > 0)
                    Overflow = 1;
            end
        endcase
    end

    Carry = temp[32];
    
end
endmodule

tb_ALU.v
`timescale 1ns/1ps
`include "ALU.v"

module ALU_tb();

    // declaring inputs
    reg [31:0] A, B;
    reg [2:0] ALUControl;
    
    // declaring outputs
    wire [31:0] Result;
    wire Zero, Negative, Overflow, Carry;
    
    // instantiating ALU module
    ALU dut (
        .A(A),
        .B(B),
        .ALUControl(ALUControl),
        .Result(Result),
        .Zero(Zero),
        .Negative(Negative),
        .Overflow(Overflow),
        .Carry(Carry)
    );
    
    initial begin
        $dumpfile("ALU_sim.vcd");
        $dumpvars(0, ALU_tb);
    end
    // test logic
    initial begin
    
        // TEST 1 - ADD operation with zero result
        A = 32'd0;
        B = 32'd0;
        ALUControl = 3'b000;
        
        #10;
        
        
        // TEST 2 - ADD operation
        A = 32'd10;
        B = 32'd5;
        ALUControl = 3'b000;
        
        #10;
        
        
        // TEST 3 - ADD operation with carry
        A = 32'hFFFFFFFF;
        B = 32'd1;
        ALUControl = 3'b000;
        
        #10;
        
        
        // TEST 4 - ADD operation with overflow
        A = 32'h7FFFFFFF;
        B = 32'd1;
        ALUControl = 3'b000;
        
        #10;
        
        
        // TEST 5 - SUB operation
        A = 32'd10;
        B = 32'd5;
        ALUControl = 3'b001;
        
        #10;
        
        
        // TEST 6 - SUB operation with negative result
        A = 32'd5;
        B = 32'd10;
        ALUControl = 3'b001;
        
        #10;
        
        
        // TEST 7 - SUB operation with overflow
        A = 32'h80000000;
        B = 32'd1;
        ALUControl = 3'b001;
        
        #10;
        
        
        // TEST 8 - AND operation
        A = 32'hF0F0F0F0;
        B = 32'h0F0F0F0F;
        ALUControl = 3'b010;
        
        #10;
        
        
        // TEST 9 - OR operation
        A = 32'hF0F0F0F0;
        B = 32'h0F0F0F0F;
        ALUControl = 3'b011;
        
        #10;
        
        
        // TEST 10 - SLT operation
        A = 32'd5;
        B = 32'd10;
        ALUControl = 3'b101;
        
        #10;
        
        
        // ending simulation
        $finish;
        
    end

endmodule

ALU_sim.vcd
$date
	Fri Sep 25 21:40:14 2026
$end
$version
	Icarus Verilog
$end
$timescale
	1ps
$end
$scope module ALU_tb $end
$var wire 1 ! Zero $end
$var wire 32 " Result [31:0] $end
$var wire 1 # Overflow $end
$var wire 1 $ Negative $end
$var wire 1 % Carry $end
$var reg 32 & A [31:0] $end
$var reg 3 ' ALUControl [2:0] $end
$var reg 32 ( B [31:0] $end
$scope module dut $end
$var wire 32 ) A [31:0] $end
$var wire 3 * ALUControl [2:0] $end
$var wire 32 + B [31:0] $end
$var parameter 3 , ADD $end
$var parameter 3 - AND $end
$var parameter 3 . OR $end
$var parameter 3 / SLT $end
$var parameter 3 0 SUB $end
$var reg 1 % Carry $end
$var reg 1 $ Negative $end
$var reg 1 # Overflow $end
$var reg 32 1 Result [31:0] $end
$var reg 1 ! Zero $end
$var reg 33 2 temp [32:0] $end
$upscope $end
$upscope $end
$enddefinitions $end
$comment Show the parameter values. $end
$dumpall
b1 0
b101 /
b11 .
b10 -
b0 ,
$end
#0
$dumpvars
b0 2
b0 1
b0 +
b0 *
b0 )
b0 (
b0 '
b0 &
0%
0$
0#
b0 "
1!
$end
#10000
b1111 "
b1111 1
b1111 2
0!
b101 (
b101 +
b1010 &
b1010 )
#20000
1%
1!
b0 "
b0 1
b100000000000000000000000000000000 2
b1 (
b1 +
b11111111111111111111111111111111 &
b11111111111111111111111111111111 )
#30000
1$
1#
b10000000000000000000000000000000 "
b10000000000000000000000000000000 1
b10000000000000000000000000000000 2
0%
0!
b1111111111111111111111111111111 &
b1111111111111111111111111111111 )
#40000
b101 "
b101 1
0#
0$
b1 '
b1 *
b101 (
b101 +
b1010 &
b1010 )
#50000
1$
b11111111111111111111111111111011 "
b11111111111111111111111111111011 1
b1010 (
b1010 +
b101 &
b101 )
#60000
1#
b1111111111111111111111111111111 "
b1111111111111111111111111111111 1
0$
b1 (
b1 +
b10000000000000000000000000000000 &
b10000000000000000000000000000000 )
#70000
1!
b0 "
b0 1
0#
b10 '
b10 *
b1111000011110000111100001111 (
b1111000011110000111100001111 +
b11110000111100001111000011110000 &
b11110000111100001111000011110000 )
#80000
1$
b11111111111111111111111111111111 "
b11111111111111111111111111111111 1
0!
b11 '
b11 *
#90000
b1 "
b1 1
0$
b101 '
b101 *
b1010 (
b1010 +
b101 &
b101 )
